pyral/__init__.py
pyral/cargotruck.py
pyral/config.py
pyral/context.py
pyral/entity.py
pyral/hydrate.py
pyral/query_builder.py
pyral/rallyresp.py
pyral/restapi.py
pyral/search_utils.py
pyral-1.6.0.dist-info/LICENSE
pyral-1.6.0.dist-info/METADATA
pyral-1.6.0.dist-info/WHEEL
pyral-1.6.0.dist-info/top_level.txt
pyral-1.6.0.dist-info/RECORD
