Metadata-Version: 2.1
Name: pyral
Version: 1.6.0
Summary: Python toolkit for Rally REST API
Home-page: https://github.com/RallyTools/RallyRestToolkitForPython
Download-URL: https://github.com/RallyTools/RallyRestToolkitForPython/raw/master/dists/pyral-1.6.0.zip
Author: Kip Lehman (Broadcom, Agile Operations Division)
Author-email: kip.lehman@broadcom.com
License: BSD
Keywords: rally,api
Classifier: Development Status :: 5 - Production/Stable
Classifier: Environment :: Web Environment
Classifier: Intended Audience :: Developers
Classifier: License :: OSI Approved :: BSD License
Classifier: Operating System :: OS Independent
Classifier: Programming Language :: Python
Classifier: Programming Language :: Python :: 3.9
Classifier: Programming Language :: Python :: 3.10
Classifier: Programming Language :: Python :: 3.11
Classifier: Programming Language :: Python :: 3.12
Classifier: Topic :: Internet :: WWW/HTTP
Classifier: Topic :: Software Development :: Libraries
Requires-Python: >=3.9
License-File: LICENSE
Requires-Dist: requests >=2.28.1
